sonus_av/__init__.py
sonus_av/audio.py
sonus_av/image.py
sonus_av-0.1.0.dist-info/LICENCE.md
sonus_av-0.1.0.dist-info/METADATA
sonus_av-0.1.0.dist-info/WHEEL
sonus_av-0.1.0.dist-info/RECORD
