Metadata-Version: 2.1
Name: sonus-av
Version: 0.1.0
Summary: A library to add voice and image input support to large language models (LLMs).
Author: tknishh
Author-email: tanishqkhandelwaltqk011@gmail.com
Requires-Python: >=3.9,<3.12
Classifier: Programming Language :: Python :: 3
Classifier: Programming Language :: Python :: 3.9
Classifier: Programming Language :: Python :: 3.10
Classifier: Programming Language :: Python :: 3.11
Requires-Dist: deep-translator (>=1.11.4,<2.0.0)
Requires-Dist: google-transliteration-api (>=1.0.3,<2.0.0)
Requires-Dist: imgcat (>=0.5.0,<0.6.0)
Requires-Dist: openai (>=1.23.2,<2.0.0)
Requires-Dist: pillow (>=10.3.0,<11.0.0)
Requires-Dist: pyaudio (>=0.2.14,<0.3.0)
Requires-Dist: pybase64 (>=1.3.2,<2.0.0)
Requires-Dist: pytesseract (>=0.3.10,<0.4.0)
Requires-Dist: requests (>=2.31.0,<3.0.0)
Requires-Dist: speechrecognition (>=3.10.3,<4.0.0)
